[{"drive_id": "26897431", "domain_id": "bj29", "file_id": "655076560a3a427b10c14a88bf8030006f4e7664", "share_id": "BLu6RUwRrLb", "name": "\u26662021.\u5b8c\u7ed3\u5267.\u4e2d\u56fd\u5185\u5730", "type": "folder", "created_at": "2023-11-12T06:53:10.273Z", "updated_at": "2023-11-12T06:53:10.273Z", "parent_file_id": "6488363c7b01e4fe394a414db149e72b550fa04b"}, {"drive_id": "26897431", "domain_id": "bj29", "file_id": "6377df188427eff609104bea93fc27ec3beddcf8", "share_id": "BLu6RUwRrLb", "name": "\u26662022.\u5b8c\u7ed3\u5267.\u4e2d\u56fd\u5185\u5730", "type": "folder", "created_at": "2022-11-18T19:38:00.536Z", "updated_at": "2023-06-13T23:09:33.993Z", "parent_file_id": "6488363c7b01e4fe394a414db149e72b550fa04b"}, {"drive_id": "26897431", "domain_id": "bj29", "file_id": "64576375a99be9fd7d584d398ed291c335ef2a92", "share_id": "BLu6RUwRrLb", "name": "\u26662023.\u5b8c\u7ed3\u5267.\u4e2d\u56fd\u5185\u5730", "type": "folder", "created_at": "2023-05-07T08:38:13.469Z", "updated_at": "2023-06-13T23:05:22.519Z", "parent_file_id": "6488363c7b01e4fe394a414db149e72b550fa04b"}, {"drive_id": "26897431", "domain_id": "bj29", "file_id": "65a5fcac628321a035c141599664e12d9bf5e22a", "share_id": "BLu6RUwRrLb", "name": "\u26662024.\u5b8c\u7ed3\u5267.\u4e2d\u56fd\u5185\u5730", "type": "folder", "created_at": "2024-01-16T03:49:00.800Z", "updated_at": "2024-01-16T03:49:00.800Z", "parent_file_id": "6488363c7b01e4fe394a414db149e72b550fa04b"}, {"drive_id": "26897431", "domain_id": "bj29", "file_id": "6377dfd90ea63330775b4b45b1d6df772729f3a9", "share_id": "BLu6RUwRrLb", "name": "\u2666\u88ab\u4e0b\u67b6\u5267", "type": "folder", "created_at": "2022-11-18T19:41:13.135Z", "updated_at": "2023-06-13T09:26:22.582Z", "parent_file_id": "6488363c7b01e4fe394a414db149e72b550fa04b"}, {"drive_id": "26897431", "domain_id": "bj29", "file_id": "6377dfc9fc6452e827f44d8b962e549cbc345c8b", "share_id": "BLu6RUwRrLb", "name": "\u2666\u8fd1\u671f\u5b8c\u7ed3(\u5fae)\u77ed\u5267", "type": "folder", "created_at": "2022-11-18T19:40:57.662Z", "updated_at": "2023-06-13T09:26:22.586Z", "parent_file_id": "6488363c7b01e4fe394a414db149e72b550fa04b"}, {"drive_id": "26897431", "domain_id": "bj29", "file_id": "6377dfe29d30b9a2071b4afa89f782220df1d362", "share_id": "BLu6RUwRrLb", "name": "\u2666\u8fd1\u671f\u5b8c\u7ed3\u5267\uff08\u4e2d\u56fd\u53f0\u6e7e\uff09", "type": "folder", "created_at": "2022-11-18T19:41:22.345Z", "updated_at": "2023-06-13T09:26:22.579Z", "parent_file_id": "6488363c7b01e4fe394a414db149e72b550fa04b"}, {"drive_id": "26897431", "domain_id": "bj29", "file_id": "6377dfe340314a8279bf4acea2ec44504db712d9", "share_id": "BLu6RUwRrLb", "name": "\u2666\u8fd1\u671f\u5b8c\u7ed3\u5267\uff08\u4e2d\u56fd\u9999\u6e2f\uff09", "type": "folder", "created_at": "2022-11-18T19:41:23.579Z", "updated_at": "2023-06-13T09:26:22.582Z", "parent_file_id": "6488363c7b01e4fe394a414db149e72b550fa04b"}, {"drive_id": "26897431", "domain_id": "bj29", "file_id": "645763fb2d742ef2c4ac452dada748aad10cfb1f", "share_id": "BLu6RUwRrLb", "name": "\u2666\u8fd1\u671f\u5b8c\u7ed3\u9ad8\u5206\u5267", "type": "folder", "created_at": "2023-05-07T08:40:27.385Z", "updated_at": "2023-12-06T18:52:28.228Z", "parent_file_id": "6488363c7b01e4fe394a414db149e72b550fa04b"}]